wccls/__init__.py
wccls/bibliocommons.py
wccls/item_types.py
wccls/parser.py
wccls/py.typed
wccls-4.0.1.dist-info/METADATA
wccls-4.0.1.dist-info/WHEEL
wccls-4.0.1.dist-info/licenses/LICENSE
wccls-4.0.1.dist-info/RECORD
