Metadata-Version: 2.4
Name: wccls
Version: 4.0.1
Summary: Scraper for the WCCLS account page
Project-URL: Homepage, https://github.com/rkhwaja/wccls
Maintainer-email: Rehan Khwaja <rehan@khwaja.name>
License-Expression: MIT
License-File: LICENSE
Classifier: Development Status :: 5 - Production/Stable
Classifier: Intended Audience :: Developers
Classifier: Programming Language :: Python :: 3.9
Classifier: Programming Language :: Python :: 3.10
Classifier: Programming Language :: Python :: 3.11
Classifier: Programming Language :: Python :: 3.12
Classifier: Programming Language :: Python :: 3.13
Classifier: Programming Language :: Python :: 3.14
Requires-Python: >=3.9
Requires-Dist: aiohttp>=3.9
Requires-Dist: beautifulsoup4>=4.9.3
Requires-Dist: requests>=2.25.1
Requires-Dist: urllib3>=1.26; python_full_version >= '3.10'
